memium/__init__.py
memium/__main__.py
memium/diff_determiner.py
memium/environment.py
memium/py.typed
memium/test_diff_determiner.py
memium/test_main.py
memium/destination/__init__.py
memium/destination/destination.py
memium/destination/destination_ankiconnect.py
memium/destination/destination_dryrun.py
memium/destination/test_destination_ankiconnect.py
memium/destination/ankiconnect/__init__.py
memium/destination/ankiconnect/anki_converter.py
memium/destination/ankiconnect/anki_formatter.py
memium/destination/ankiconnect/anki_model.py
memium/destination/ankiconnect/anki_prompt_qa.py
memium/destination/ankiconnect/ankiconnect_gateway.py
memium/destination/ankiconnect/default_styling.css
memium/destination/ankiconnect/test_anki_converter.py
memium/destination/ankiconnect/test_anki_prompt_qa.py
memium/destination/ankiconnect/test_ankiconnect_gateway.py
memium/destination/ankiconnect/test_styling.html
memium/destination/ankiconnect/__snapshots__/test_anki_prompt_qa.ambr
memium/raw_processors/test_title_as_answer.py
memium/raw_processors/title_as_answer.py
memium/source/__init__.py
memium/source/document.py
memium/source/document_source.py
memium/source/prompt.py
memium/source/prompt_source.py
memium/source/test_document_source.py
memium/source/test_facade.py
memium/source/test_prompt_qa.py
memium/source/test_prompt_source.py
memium/source/__snapshots__/prompt_from_doc_test.ambr
memium/source/extractors/__init__.py
memium/source/extractors/extractor.py
memium/source/extractors/extractor_qa.py
memium/source/extractors/extractor_table.py
memium/source/extractors/test_extractor_table.py
memium/source/extractors/test_prompt_extractor_qa.py
memium/source/extractors/to_line_blocks.py
memium/tasks/__init__.py
memium/tasks/smoketest.py
memium/tasks/str_parsing.py
memium/utils/__init__.py
memium/utils/code_block.md
memium/utils/hash_cleaned_str.py
memium/utils/markdown.py
memium/utils/test_hash_cleaned_str.py
memium/utils/test_markdown.py
memium-1.10.0.dist-info/METADATA
memium-1.10.0.dist-info/WHEEL
memium-1.10.0.dist-info/entry_points.txt
memium-1.10.0.dist-info/top_level.txt
memium-1.10.0.dist-info/RECORD
