Metadata-Version: 2.4
Name: memium
Version: 1.10.0
Summary: Memium
Author-email: Martin Bernstorff <martinbernstorff@gmail.com>
Project-URL: homepage, https://github.com/MartinBernstorff/memium
Project-URL: repository, https://github.com/MartinBernstorff/memium
Project-URL: documentation, https://MartinBernstorff.github.io/memium/
Classifier: Programming Language :: Python :: 3.11
Requires-Python: >=3.11
Requires-Dist: bs4==0.0.2
Requires-Dist: cffi==2.0.0
Requires-Dist: genanki==0.13.1
Requires-Dist: iterpy==1.12.0
Requires-Dist: markdown==3.10
Requires-Dist: pydantic==2.12.5
Requires-Dist: sentry-sdk==2.48.0
Requires-Dist: typer==0.21.0
Requires-Dist: tqdm==4.67.1
Requires-Dist: unidecode==1.4.0
Requires-Dist: wasabi==1.1.3
Requires-Dist: inline-snapshot>=0.22.0
